{"cameraMode":{"drawMode":0,"name":"Shaded","section":"Shading Mode"},"sceneLighting":true,"audioPlay":false,"sceneViewState":{"showFog":true,"showMaterialUpdate":false,"showSkybox":true,"showFlares":true,"showImageEffects":true,"showParticleSystems":true},"in2DMode":false,"pivot":{"x":345.8106994628906,"y":660.0457763671875,"z":6.356292724609375},"rotation":{"x":0.03538499027490616,"y":0.017987573519349099,"z":-0.0006369648035615683,"w":0.9992123246192932},"size":220.26446533203126,"orthographic":false}